bxgraph/__init__.py
bxgraph/algorithms/__init__.py
bxgraph/algorithms/build.py
bxgraph/algorithms/func.py
bxgraph/algorithms/generate.py
bxgraph/algorithms/stats.py
bxgraph/backend/__init__.py
bxgraph/backend/base.py
bxgraph/backend/numpy.py
bxgraph/utils/__init__.py
bxgraph/utils/numpy.py
bxgraph/walker/__init__.py
bxgraph/walker/base.py
bxgraph/walker/node2vec.py
tests/__init__.py
tests/build_tests.py
tests/stats_tests.py
BxGraph-0.4.1.dist-info/LICENSE
BxGraph-0.4.1.dist-info/METADATA
BxGraph-0.4.1.dist-info/WHEEL
BxGraph-0.4.1.dist-info/top_level.txt
BxGraph-0.4.1.dist-info/RECORD
