Metadata-Version: 2.1
Name: BxGraph
Version: 0.4.1
Summary: Graph Management in Python.
Home-page: https://gitlab.lrz.de/borchero/bxgraph
Author: Oliver Borchert
Author-email: borchero@icloud.com
License: License :: OSI Approved :: MIT License
Platform: UNKNOWN
Classifier: Development Status :: 4 - Beta
Classifier: Programming Language :: Python :: 3.7
Classifier: Topic :: Software Development :: Libraries
Requires-Python: >=3.7
Requires-Dist: numpy (<2.0.0,>=1.18.1)
Requires-Dist: scipy (<2.0.0,>=1.4.1)
Requires-Dist: numba (<0.48.0,>=0.47.0)
